proclip/__init__.py
proclip/errors.py
proclip/py.typed
proclip/types.py
proclip/ux.py
proclip/api/__init__.py
proclip/api/clips.py
proclip/cli/__init__.py
proclip/cli/clip/__init__.py
proclip/cli/clip/clip.py
proclip/cli/clip/new.py
proclip/cli/clip/paste.py
proclip-0.2.0.dist-info/LICENSE
proclip-0.2.0.dist-info/METADATA
proclip-0.2.0.dist-info/WHEEL
proclip-0.2.0.dist-info/entry_points.txt
proclip-0.2.0.dist-info/top_level.txt
proclip-0.2.0.dist-info/RECORD
